cachish/__init__.py
cachish/_version.py
cachish/auth.py
cachish/cache.py
cachish/utils.py
cachish/backends/__init__.py
cachish/backends/hawk_json_http.py
cachish/backends/heroku.py
cachish/backends/json_http.py
cachish-1.7.0.dist-info/LICENSE
cachish-1.7.0.dist-info/METADATA
cachish-1.7.0.dist-info/WHEEL
cachish-1.7.0.dist-info/top_level.txt
cachish-1.7.0.dist-info/RECORD
